pyjake.py
pyjake_constants.py
pyjake_packets.py
pyjake_serial_pc.py
jake_drivers-1.0.1.dist-info/DESCRIPTION.rst
jake_drivers-1.0.1.dist-info/METADATA
jake_drivers-1.0.1.dist-info/RECORD
jake_drivers-1.0.1.dist-info/WHEEL
jake_drivers-1.0.1.dist-info/metadata.json
jake_drivers-1.0.1.dist-info/top_level.txt
