Metadata-Version: 2.0
Name: jake-drivers
Version: 1.0.1
Summary: JAKE sensor device driver
Home-page: https://github.com/andrewramsay/jake-drivers
Author: Andrew Ramsay
Author-email: andrew.ramsay@glasgow.ac.uk
License: BSD
Keywords: development sensors sensing JAKE
Platform: UNKNOWN
Classifier: Development Status :: 5 - Production/Stable
Classifier: Intended Audience :: Developers
Classifier: License :: OSI Approved :: BSD License
Classifier: Programming Language :: Python :: 2
Classifier: Programming Language :: Python :: 2.6
Classifier: Programming Language :: Python :: 2.7
Classifier: Programming Language :: Python :: 3
Classifier: Programming Language :: Python :: 3.3
Classifier: Programming Language :: Python :: 3.4
Classifier: Programming Language :: Python :: 3.5
Requires-Dist: pyserial
